clustermatch/__init__.py
clustermatch/cluster.py
clustermatch/main.py
clustermatch/utils/__init__.py
clustermatch/utils/data.py
clustermatch/utils/methods.py
clustermatch/utils/misc.py
clustermatch/utils/output.py
clustermatch-0.1.5.dist-info/LICENSE
clustermatch-0.1.5.dist-info/METADATA
clustermatch-0.1.5.dist-info/WHEEL
clustermatch-0.1.5.dist-info/entry_points.txt
clustermatch-0.1.5.dist-info/top_level.txt
clustermatch-0.1.5.dist-info/RECORD
