Metadata-Version: 2.1
Name: clustermatch
Version: 0.1.5
Summary: Efficient clustering method for processing highly diverse data
Home-page: https://github.com/sinc-lab/clustermatch
Author: Milton Pividori
Author-email: miltondp@gmail.com
License: MIT
Platform: UNKNOWN
Classifier: Programming Language :: Python :: 3
Classifier: License :: OSI Approved :: MIT License
Classifier: Operating System :: OS Independent
Classifier: Development Status :: 5 - Production/Stable
Classifier: Environment :: Console
Requires-Python: >=3
Requires-Dist: numpy
Requires-Dist: scipy
Requires-Dist: pandas
Requires-Dist: joblib
Requires-Dist: scikit-learn
Requires-Dist: xlrd
Requires-Dist: xlwt
Requires-Dist: openpyxl
